LICENSE
MANIFEST.in
README.rst
setup.py
pyAS2.egg-info/PKG-INFO
pyAS2.egg-info/SOURCES.txt
pyAS2.egg-info/dependency_links.txt
pyAS2.egg-info/requires.txt
pyAS2.egg-info/top_level.txt
pyas2/__init__.py
pyas2/admin.py
pyas2/as2lib.py
pyas2/as2utils.py
pyas2/forms.py
pyas2/models.py
pyas2/pyas2init.py
pyas2/test_settings.py
pyas2/urls.py
pyas2/viewlib.py
pyas2/views.py
pyas2/management/__init__.py
pyas2/management/__init__.pyc
pyas2/management/commands/__init__.py
pyas2/management/commands/__init__.pyc
pyas2/management/commands/cleanas2server.py
pyas2/management/commands/retryfailedas2comms.py
pyas2/management/commands/runas2daemon.py
pyas2/management/commands/runas2server.py
pyas2/management/commands/runas2server.pyc
pyas2/management/commands/sendas2message.py
pyas2/management/commands/sendas2message.pyc
pyas2/management/commands/sendasyncmdn.py
pyas2/migrations/0001_initial.py
pyas2/migrations/0001_initial.pyc
pyas2/migrations/0002_partner_compress.py
pyas2/migrations/0002_partner_compress.pyc
pyas2/migrations/0003_auto_20150311_1141.py
pyas2/migrations/0003_auto_20150311_1141.pyc
pyas2/migrations/0004_auto_20150311_1258.py
pyas2/migrations/0004_auto_20150311_1258.pyc
pyas2/migrations/0005_message_compressed.py
pyas2/migrations/0005_message_compressed.pyc
pyas2/migrations/0006_auto_20150313_0548.py
pyas2/migrations/0006_auto_20150313_0548.pyc
pyas2/migrations/0007_auto_20150313_0707.py
pyas2/migrations/0007_auto_20150313_0707.pyc
pyas2/migrations/0008_auto_20150317_0450.py
pyas2/migrations/0008_auto_20150317_0450.pyc
pyas2/migrations/0009_auto_20150317_1324.py
pyas2/migrations/0009_auto_20150317_1324.pyc
pyas2/migrations/0010_auto_20150416_0745.py
pyas2/migrations/0010_auto_20150416_0745.pyc
pyas2/migrations/0011_auto_20150427_1029.py
pyas2/migrations/0011_auto_20150427_1029.pyc
pyas2/migrations/0012_auto_20151006_0526.py
pyas2/migrations/0012_auto_20151006_0526.pyc
pyas2/migrations/0013_auto_20160307_0233.py
pyas2/migrations/0013_auto_20160307_0233.pyc
pyas2/migrations/0014_auto_20160420_0515.py
pyas2/migrations/0014_auto_20160420_0515.pyc
pyas2/migrations/0015_auto_20160615_0409.py
