Metadata-Version: 1.1
Name: pyAS2
Version: 0.4.6
Summary: A pythonic AS2 application for file tranfers.
Home-page: http://pyas2.readthedocs.org/en/latest/
Author: Abhishek Ram
Author-email: abhishek8816@gmail.com
License: GNU GPL v2.0
Download-URL: https://github.com/abhishek-ram/pyas2/archive/master.zip
Keywords: AS2 AS2Server RFC4130 FileTransfer
Platform: UNKNOWN
Classifier: Development Status :: 5 - Production/Stable
Classifier: Environment :: Web Environment
Classifier: Framework :: Django
Classifier: Intended Audience :: Developers
Classifier: License :: OSI Approved :: GNU General Public License v2 (GPLv2)
Classifier: Operating System :: OS Independent
Classifier: Programming Language :: Python
Classifier: Programming Language :: Python :: 2
Classifier: Programming Language :: Python :: 2.6
Classifier: Programming Language :: Python :: 2.7
Classifier: Topic :: Internet :: WWW/HTTP
Classifier: Topic :: Internet :: WWW/HTTP :: WSGI
Classifier: Topic :: Internet :: WWW/HTTP :: WSGI :: Middleware
